hydroDL/__init__.py
hydroDL/__version__.py
hydroDL/dataset.py
hydroDL/core/__init__.py
hydroDL/core/logger.py
hydroDL/core/read.py
hydroDL/data/__init__.py
hydroDL/data/camels.py
hydroDL/data/dbCsv.py
hydroDL/data/dbModis.py
hydroDL/data/load_csv.py
hydroDL/deprecated/__init__.py
hydroDL/deprecated/geo.py
hydroDL/master/__init__.py
hydroDL/master/default.py
hydroDL/master/master.py
hydroDL/master/screen.py
hydroDL/model/__init__.py
hydroDL/model/crit.py
hydroDL/model/dropout.py
hydroDL/model/functions.py
hydroDL/model/settings.py
hydroDL/model/test.py
hydroDL/model/train.py
hydroDL/model/train_multi.py
hydroDL/model/cnn/CNN1dkernel.py
hydroDL/model/cnn/Cnn1d.py
hydroDL/model/cnn/LstmCnn1d.py
hydroDL/model/cnn/__init__.py
hydroDL/model/cnn/functions.py
hydroDL/model/data/__init__.py
hydroDL/model/data/load/__init__.py
hydroDL/model/data/load/test/__init__.py
hydroDL/model/data/load/test/default.py
hydroDL/model/data/load/test/parameter.py
hydroDL/model/data/load/test/permute.py
hydroDL/model/data/load/test/z_data.py
hydroDL/model/data/load/train/__init__.py
hydroDL/model/data/load/train/default.py
hydroDL/model/data/load/train/parameter.py
hydroDL/model/data/load/train/permute.py
hydroDL/model/data/load/train/z_data.py
hydroDL/model/data/post_process/__init__.py
hydroDL/model/data/post_process/default.py
hydroDL/model/data/post_process/parameter.py
hydroDL/model/data/post_process/permute.py
hydroDL/model/data/post_process/yss.py
hydroDL/model/rnn/AnnCloseModel.py
hydroDL/model/rnn/AnnModel.py
hydroDL/model/rnn/CNN1dLCInmodel.py
hydroDL/model/rnn/CNN1dLCmodel.py
hydroDL/model/rnn/CNN1dLSTMInmodel.py
hydroDL/model/rnn/CNN1dLSTMmodel.py
hydroDL/model/rnn/CpuLstmModel.py
hydroDL/model/rnn/CudnnInvLstmModel.py
hydroDL/model/rnn/CudnnLstm.py
hydroDL/model/rnn/CudnnLstmModel.py
hydroDL/model/rnn/CudnnLstmModel_R2P.py
hydroDL/model/rnn/Hymod.py
hydroDL/model/rnn/LSTMcell_tied.py
hydroDL/model/rnn/LSTMcell_untied.py
hydroDL/model/rnn/LstmCloseModel.py
hydroDL-0.1.5.dist-info/LICENSE
hydroDL-0.1.5.dist-info/METADATA
hydroDL-0.1.5.dist-info/WHEEL
hydroDL-0.1.5.dist-info/top_level.txt
hydroDL-0.1.5.dist-info/RECORD
