Metadata-Version: 2.1
Name: hydroDL
Version: 0.1.5
Summary: Hydrological Deep Learning
Home-page: https://github.com/mhpi/hydroDL/
Author: MHPI
Author-email: cshen@engr.psu.edu
License: Non-Commercial Software License
Classifier: Programming Language :: Python
Classifier: Programming Language :: Python :: 3
Classifier: Programming Language :: Python :: Implementation :: CPython
Classifier: Programming Language :: Python :: Implementation :: PyPy
Requires-Python: >=3.0
License-File: LICENSE
Requires-Dist: torch ==2.1.1
Requires-Dist: matplotlib ==3.8.0
Requires-Dist: cartopy
Requires-Dist: numpy
Requires-Dist: pandas ==2.1.1
Requires-Dist: scipy
Requires-Dist: statsmodels
Requires-Dist: tqdm
